vaultdb-0.10.3.dev1901.dist-info/RECORD
vaultdb-0.10.3.dev1901.dist-info/WHEEL
vaultdb-0.10.3.dev1901.dist-info/top_level.txt
vaultdb-0.10.3.dev1901.dist-info/METADATA
duckdb-stubs/__init__.pyi
duckdb-stubs/value/__init__.pyi
duckdb-stubs/value/constant/__init__.pyi
duckdb-stubs/typing/__init__.pyi
duckdb-stubs/functional/__init__.pyi
duckdb-stubs/login/__init__.pyi
duckdb/filesystem.py
duckdb/__init__.py
duckdb/duckdb.cpython-310-darwin.so
duckdb/bytes_io_wrapper.py
duckdb/udf.py
duckdb/experimental/__init__.py
duckdb/experimental/spark/exception.py
duckdb/experimental/spark/_typing.py
duckdb/experimental/spark/LICENSE
duckdb/experimental/spark/_globals.py
duckdb/experimental/spark/conf.py
duckdb/experimental/spark/__init__.py
duckdb/experimental/spark/context.py
duckdb/experimental/spark/errors/error_classes.py
duckdb/experimental/spark/errors/__init__.py
duckdb/experimental/spark/errors/utils.py
duckdb/experimental/spark/errors/exceptions/__init__.py
duckdb/experimental/spark/errors/exceptions/base.py
duckdb/experimental/spark/sql/catalog.py
duckdb/experimental/spark/sql/functions.py
duckdb/experimental/spark/sql/_typing.py
duckdb/experimental/spark/sql/dataframe.py
duckdb/experimental/spark/sql/conf.py
duckdb/experimental/spark/sql/session.py
duckdb/experimental/spark/sql/type_utils.py
duckdb/experimental/spark/sql/__init__.py
duckdb/experimental/spark/sql/types.py
duckdb/experimental/spark/sql/readwriter.py
duckdb/experimental/spark/sql/group.py
duckdb/experimental/spark/sql/udf.py
duckdb/experimental/spark/sql/streaming.py
duckdb/experimental/spark/sql/column.py
duckdb/query_graph/__main__.py
duckdb/value/constant.py
duckdb/typing/__init__.py
duckdb/functional/__init__.py
duckdb/login/cognito.py
duckdb/login/__init__.py
adbc_driver_duckdb/dbapi.py
adbc_driver_duckdb/__init__.py
