Metadata-Version: 2.1
Name: vaultdb
Version: 0.10.3.dev1901
Summary: VaultDB embedded database
Home-page: http://www.vaultdb.ai
Maintainer: vaultdb.ai
Maintainer-email: support@vaultdb.ai
License: BSD
Project-URL: Documentation, https://docs.vaultdb.ai
Project-URL: Issues, https://github.com/vaultdbai/quickstart/issues
Project-URL: Changelog, https://github.com/vaultdbai/quickstart/releases
Keywords: VaultDB Database SQL OLAP AI
Classifier: Topic :: Database :: Database Engines/Servers
Classifier: Intended Audience :: Developers
Classifier: License :: OSI Approved :: BSD License
Requires-Python: >=3.8.0
